{
  "execution_id": "6aab6084-226b-420a-96dc-d4b6cdf644d2",
  "entries": [
    {
      "entry_id": 0,
      "timestamp": "2025-05-20T12:20:08.700477Z",
      "event_type": "input",
      "event_data": {
        "type": "execution_initialization",
        "trigger_type": "cli",
        "trigger_id": "test-trigger-011",
        "random_seed": "73a8d6c3-b2f3-43af-a4c4-306c5dc3bd94"
      },
      "previous_hash": "0000000000000000000000000000000000000000000000000000000000000000",
      "current_hash": "ec7631cbb5d1c53ed9b85ec81c1f17bbefdb226d75a4a7fa4d693568809b8da8"
    },
    {
      "entry_id": 1,
      "timestamp": "2025-05-20T12:20:08.700503Z",
      "event_type": "input",
      "event_data": {
        "type": "loop_input",
        "content": {
          "loop_id": "30fc0225-12a2-485c-9003-425e5f4607e9",
          "plan_details": {
            "test": "plan input"
          },
          "operator_override_signal": null
        }
      },
      "previous_hash": "ec7631cbb5d1c53ed9b85ec81c1f17bbefdb226d75a4a7fa4d693568809b8da8",
      "current_hash": "3cdca93b80c5303edf036f94d0c530c462e443ca1566ff78f285241806112e0b"
    },
    {
      "entry_id": 2,
      "timestamp": "2025-05-20T12:20:08.700608Z",
      "event_type": "output",
      "event_data": {
        "type": "core_output",
        "content": [
          {
            "status": "mock_success",
            "details": "GovernanceCore mock executed successfully.",
            "received_plan_input": {
              "loop_id": "30fc0225-12a2-485c-9003-425e5f4607e9",
              "plan_details": {
                "test": "plan input"
              },
              "operator_override_signal": null
            },
            "received_override": null
          },
          {
            "timestamp": "2025-05-20T12:20:08.700539Z",
            "current_emotion_state": "MOCK_FOCUSED",
            "contributing_factors": [
              {
                "factor": "Mock Clarity of Task",
                "influence": 0.9
              }
            ],
            "trust_score": 0.95
          },
          {
            "agent_id": "Promethios_MGC_v1_mock",
            "timestamp": "2025-05-20T12:20:08.700539Z",
            "plan_id": "mock_plan_id_b780475b-a700-4b3a-94ef-2908b4ed49eb",
            "loop_id": "573adc41-83e7-421b-b1dd-46891c76a1ca",
            "decision_outcome": "MOCK_ACCEPTED",
            "rejection_reason": null,
            "override_required": false,
            "trust_score_at_decision": 0.95,
            "emotion_state_at_decision": "MOCK_FOCUSED",
            "validation_passed": true,
            "schema_versions": {
              "emotion_telemetry": "mgc_emotion_telemetry.schema.json#v_mock",
              "justification_log": "loop_justification_log.schema.v1.json#v1.2.0_mock"
            },
            "override_active": false,
            "override_type": null,
            "override_reason": null,
            "override_parameters": null,
            "override_issuing_operator_id": null
          }
        ]
      },
      "previous_hash": "3cdca93b80c5303edf036f94d0c530c462e443ca1566ff78f285241806112e0b",
      "current_hash": "b642e63d0d9230e0ea69b6e5ea6183f22402b4d10d794977d4fe2266a93cd97b"
    }
  ],
  "metadata": {
    "contract_version": "v2025.05.20",
    "phase_id": "5.2",
    "trigger_type": "cli",
    "trigger_id": "test-trigger-011",
    "start_time": "2025-05-20T12:20:08.700333Z",
    "end_time": "2025-05-20T12:20:08.700802Z",
    "random_seed": "354944f8-1726-4e1a-a9f1-86b5e403ad75",
    "environment_hash": "7c2efbb1b561a812ef5cb03a87764acc69c7e4c1811661a468675d30ea941066"
  }
}